django_hidden_models/__init__.py
django_hidden_models/asgi.py
django_hidden_models/settings.py
django_hidden_models/urls.py
django_hidden_models/wsgi.py
hidden_models/__init__.py
hidden_models/apps.py
hidden_models/managers.py
hidden_models/models.py
hidden_models/queryset.py
your_app/__init__.py
your_app/admin.py
your_app/apps.py
your_app/models.py
your_app/tests.py
your_app/views.py
your_app/migrations/0001_initial.py
your_app/migrations/__init__.py
django_hidden_models-0.1.0.dist-info/AUTHORS
django_hidden_models-0.1.0.dist-info/LICENSE.txt
django_hidden_models-0.1.0.dist-info/METADATA
django_hidden_models-0.1.0.dist-info/WHEEL
django_hidden_models-0.1.0.dist-info/top_level.txt
django_hidden_models-0.1.0.dist-info/RECORD
