Metadata-Version: 2.1
Name: django-hidden-models
Version: 0.1.0
Summary: Simply hiding a useless data from query results
Home-page: https://github.com/bigcrazyfrog/django-hidden-models
Author: Nikita Cibin
Author-email: cibinnikita@gmail.com
License: BSD
Keywords: django,hidden,hide,visible,models
Classifier: License :: OSI Approved :: BSD License
Classifier: Operating System :: OS Independent
Classifier: Programming Language :: Python
Classifier: Programming Language :: Python :: 3
Classifier: Programming Language :: Python :: 3.8
Classifier: Programming Language :: Python :: 3.9
Classifier: Programming Language :: Python :: 3.10
Classifier: Programming Language :: Python :: 3.11
Classifier: Programming Language :: Python :: 3.12
Classifier: Framework :: Django
Classifier: Framework :: Django :: 3.2
Classifier: Framework :: Django :: 4.0
Classifier: Framework :: Django :: 4.1
Classifier: Framework :: Django :: 4.2
Requires-Python: >=3.8
License-File: LICENSE.txt
License-File: AUTHORS
Requires-Dist: Django >=3.2
